LICENSE
MANIFEST.in
README.md
setup.py
django_emailer.egg-info/PKG-INFO
django_emailer.egg-info/SOURCES.txt
django_emailer.egg-info/dependency_links.txt
django_emailer.egg-info/requires.txt
django_emailer.egg-info/top_level.txt
emailer/__init__.py
emailer/admin.py
emailer/models.py
emailer/tests.py
emailer/fixtures/email_templates.json
emailer/migrations/0001_initial.py
emailer/migrations/__init__.py
emailer/templates/email/default.html