Metadata-Version: 1.1
Name: django-emailer
Version: 0.2.1
Summary: Template based email sending with SMTP connection management
Home-page: https://github.com/7ws/django-emailer
Author: Evandro Myller
Author-email: emyller@7ws.co
License: UNKNOWN
Keywords: django,email,smtp
Platform: UNKNOWN
Classifier: Framework :: Django
Classifier: License :: OSI Approved :: MIT License
Classifier: Programming Language :: Python :: 2.6
Classifier: Programming Language :: Python :: 2.7
Classifier: Programming Language :: Python
Classifier: Topic :: Software Development
